song_organizer/__init__.py
song_organizer/__main__.py
song_organizer/organizer.py
song_organizer-0.1.0.dist-info/LICENSE
song_organizer-0.1.0.dist-info/METADATA
song_organizer-0.1.0.dist-info/WHEEL
song_organizer-0.1.0.dist-info/entry_points.txt
song_organizer-0.1.0.dist-info/top_level.txt
song_organizer-0.1.0.dist-info/RECORD
