Metadata-Version: 2.1
Name: song_organizer
Version: 0.1.0
Summary: A Python package to organize music files by metadata.
Home-page: https://github.com/your-repo/song_organizer
Author: Your Name
Author-email: your.email@example.com
Classifier: Programming Language :: Python :: 3
Classifier: License :: OSI Approved :: MIT License
Classifier: Operating System :: OS Independent
Requires-Python: >=3.6
License-File: LICENSE
Requires-Dist: mutagen
